intellicase/__init__.py
intellicase-0.0.1.dist-info/licenses/LICENSE
intellicase-0.0.1.dist-info/METADATA
intellicase-0.0.1.dist-info/WHEEL
intellicase-0.0.1.dist-info/top_level.txt
intellicase-0.0.1.dist-info/RECORD
