Metadata-Version: 2.4
Name: intellicase
Version: 0.0.1
Summary: Intelligent AI Powered Web Browser Automation
Author-email: nerpy <nkossy.pro@gmail.com>
Classifier: Intended Audience :: Developers
Classifier: License :: OSI Approved :: Apache Software License
Classifier: Operating System :: OS Independent
Classifier: Programming Language :: Python :: 3
Requires-Python: >=3.8
License-File: LICENSE
Requires-Dist: requests
Dynamic: license-file
